Metadata-Version: 2.1
Name: simplestmaps
Version: 1.2.0
Summary: Super simple on-liner maps in python.
Home-page: http://github.com/fisadev/simplestmaps
Author: Juan Pedro Fisanotti
Author-email: fisadev@gmail.com
License: MIT
Platform: UNKNOWN
Classifier: Intended Audience :: Developers
Classifier: License :: OSI Approved :: MIT License
Classifier: Natural Language :: English
Classifier: Operating System :: OS Independent
Classifier: Programming Language :: Python
Classifier: Programming Language :: Python :: 3
